README.rst
setup.py
deparele/cli.py
deparele.egg-info/PKG-INFO
deparele.egg-info/SOURCES.txt
deparele.egg-info/dependency_links.txt
deparele.egg-info/entry_points.txt
deparele.egg-info/requires.txt
deparele.egg-info/top_level.txt