Metadata-Version: 1.1
Name: deparele
Version: 0.0.0
Summary: deparele CLI
Home-page: https://github.com/pyk/deparele
Author: Bayu Aldi Yansyah
Author-email: bayualdiyansyah@gmail.com
License: BSD 3-Clause License
Platform: UNKNOWN
Classifier: License :: OSI Approved :: BSD License
Classifier: Programming Language :: Python :: 3.6
